pygdshort/__init__.py
pygdshort/cli.py
pygdshort/link.py
pygdshort-1.1.1.dist-info/LICENSE
pygdshort-1.1.1.dist-info/METADATA
pygdshort-1.1.1.dist-info/WHEEL
pygdshort-1.1.1.dist-info/entry_points.txt
pygdshort-1.1.1.dist-info/top_level.txt
pygdshort-1.1.1.dist-info/RECORD
